odoo/addons/role_policy_account/README.rst
odoo/addons/role_policy_account/__init__.py
odoo/addons/role_policy_account/__manifest__.py
odoo/addons/role_policy_account/i18n/role_policy_account.pot
odoo/addons/role_policy_account/models/__init__.py
odoo/addons/role_policy_account/models/account_move.py
odoo/addons/role_policy_account/models/model_method_execution_right.py
odoo/addons/role_policy_account/readme/CONFIGURE.rst
odoo/addons/role_policy_account/readme/CONTRIBUTORS.rst
odoo/addons/role_policy_account/readme/DESCRIPTION.rst
odoo/addons/role_policy_account/static/description/icon.png
odoo/addons/role_policy_account/static/description/index.html
odoo13_addon_role_policy_account-13.0.1.0.1.dev16.dist-info/METADATA
odoo13_addon_role_policy_account-13.0.1.0.1.dev16.dist-info/WHEEL
odoo13_addon_role_policy_account-13.0.1.0.1.dev16.dist-info/top_level.txt
odoo13_addon_role_policy_account-13.0.1.0.1.dev16.dist-info/RECORD
